odoo/addons/account_bank_statement_chatter/README.rst
odoo/addons/account_bank_statement_chatter/__init__.py
odoo/addons/account_bank_statement_chatter/__manifest__.py
odoo/addons/account_bank_statement_chatter/i18n/account_bank_statement_chatter.pot
odoo/addons/account_bank_statement_chatter/i18n/es.po
odoo/addons/account_bank_statement_chatter/models/__init__.py
odoo/addons/account_bank_statement_chatter/models/account_bank_statement.py
odoo/addons/account_bank_statement_chatter/readme/CONTRIBUTORS.rst
odoo/addons/account_bank_statement_chatter/readme/DESCRIPTION.rst
odoo/addons/account_bank_statement_chatter/readme/USAGE.rst
odoo/addons/account_bank_statement_chatter/static/description/icon.png
odoo/addons/account_bank_statement_chatter/static/description/index.html
odoo/addons/account_bank_statement_chatter/views/account_bank_statement_views.xml
odoo12_addon_account_bank_statement_chatter-12.0.1.0.0.99.dev4.dist-info/METADATA
odoo12_addon_account_bank_statement_chatter-12.0.1.0.0.99.dev4.dist-info/WHEEL
odoo12_addon_account_bank_statement_chatter-12.0.1.0.0.99.dev4.dist-info/top_level.txt
odoo12_addon_account_bank_statement_chatter-12.0.1.0.0.99.dev4.dist-info/RECORD
