Metadata-Version: 2.1
Name: odoo12-addon-account-bank-statement-chatter
Version: 12.0.1.0.0.99.dev4
Summary: Chatter on bank statements
Home-page: https://github.com/OCA/account-financial-tools
Author: Trey, Odoo Community Association (OCA)
Author-email: support@odoo-community.org
License: AGPL-3
Platform: UNKNOWN
Classifier: Programming Language :: Python
Classifier: Framework :: Odoo
Classifier: Framework :: Odoo :: 12.0
Classifier: License :: OSI Approved :: GNU Affero General Public License v3
Classifier: Development Status :: 4 - Beta
Requires-Python: >=3.5
Requires-Dist: odoo <12.1dev,>=12.0a
